{"version":3,"kind":"Article","sha256":"9f3427d0764f5ff1bea0f4c60b9604dc83d98547ff182526014c7a304648ae74","slug":"index","location":"/intro.md","dependencies":[],"frontmatter":{"title":"Writing Template","authors":[{"id":"OpenScienceTeam","name":"OpenScienceTeam"}],"keywords":[],"exports":[{"format":"md","filename":"intro.md","url":"/intro-11ada58c23056b335ba81ae4c56e3999.md"}]},"mdast":{"type":"root","children":[{"type":"block","children":[{"type":"blockquote","position":{"start":{"line":5,"column":1},"end":{"line":5,"column":1}},"children":[{"type":"paragraph","position":{"start":{"line":5,"column":1},"end":{"line":5,"column":1}},"children":[{"type":"text","value":"For writing workflow guidelines, please refer to: ","position":{"start":{"line":5,"column":1},"end":{"line":5,"column":1}},"key":"MReNkJQBVX"},{"type":"link","url":"/writing-guide","position":{"start":{"line":5,"column":1},"end":{"line":5,"column":1}},"children":[{"type":"text","value":"Knowledge Base Authoring Guide","position":{"start":{"line":5,"column":1},"end":{"line":5,"column":1}},"key":"knrtw1qc5m"}],"urlSource":"/en/writing-guide.md","dataUrl":"/writing-guide.json","internal":true,"protocol":"file","key":"Wd6Xjr1i75"}],"key":"CouM9vkeCL"}],"key":"U1lQ4Qf3ZC"},{"type":"heading","depth":2,"position":{"start":{"line":7,"column":1},"end":{"line":7,"column":1}},"children":[{"type":"text","value":"Welcome to the MOF Learning Handbook","position":{"start":{"line":7,"column":1},"end":{"line":7,"column":1}},"key":"w3GrpKvpwF"}],"identifier":"welcome-to-the-mof-learning-handbook","label":"Welcome to the MOF Learning Handbook","html_id":"welcome-to-the-mof-learning-handbook","implicit":true,"key":"YqlcJLSyhk"},{"type":"paragraph","position":{"start":{"line":9,"column":1},"end":{"line":9,"column":1}},"children":[{"type":"text","value":"This is a sample handbook written using ","position":{"start":{"line":9,"column":1},"end":{"line":9,"column":1}},"key":"oPYe0BKD9L"},{"type":"strong","position":{"start":{"line":9,"column":1},"end":{"line":9,"column":1}},"children":[{"type":"text","value":"Jupyter Book + MyST Markdown","position":{"start":{"line":9,"column":1},"end":{"line":9,"column":1}},"key":"W14vEu7ltw"}],"key":"VfjsNmD4BV"},{"type":"text","value":", focusing on ","position":{"start":{"line":9,"column":1},"end":{"line":9,"column":1}},"key":"P7pETHdrhD"},{"type":"strong","position":{"start":{"line":9,"column":1},"end":{"line":9,"column":1}},"children":[{"type":"text","value":"MOF (Metal–Organic Frameworks)","position":{"start":{"line":9,"column":1},"end":{"line":9,"column":1}},"key":"Mz75oUcVkh"}],"key":"ON8OFSlB05"},{"type":"text","value":". It is available in both Chinese and English versions. ","position":{"start":{"line":9,"column":1},"end":{"line":9,"column":1}},"key":"G9jgT9znQm"},{"type":"link","url":"/intro-zh","position":{"start":{"line":9,"column":1},"end":{"line":9,"column":1}},"children":[{"type":"text","value":"点此进入中文版本简介","position":{"start":{"line":9,"column":1},"end":{"line":9,"column":1}},"key":"NbrK5mMpYv"}],"urlSource":"intro-zh.md","dataUrl":"/intro-zh.json","internal":true,"protocol":"file","key":"hef4xanf1I"}],"key":"pClRc183gA"},{"type":"paragraph","position":{"start":{"line":11,"column":1},"end":{"line":11,"column":1}},"children":[{"type":"text","value":"This handbook mainly demonstrates:","position":{"start":{"line":11,"column":1},"end":{"line":11,"column":1}},"key":"QZW7aIis2u"}],"key":"HHaO3zgLAV"},{"type":"list","ordered":true,"start":1,"spread":false,"position":{"start":{"line":13,"column":1},"end":{"line":22,"column":1}},"children":[{"type":"listItem","spread":true,"position":{"start":{"line":13,"column":1},"end":{"line":13,"column":1}},"children":[{"type":"paragraph","children":[{"type":"text","value":"A MOF book sample compiled with MyST Markdown.","position":{"start":{"line":13,"column":1},"end":{"line":13,"column":1}},"key":"yDIVEVgCkG"}],"key":"P0DwM2pVbY"}],"key":"YBrFbGzv8X"},{"type":"listItem","spread":true,"position":{"start":{"line":14,"column":1},"end":{"line":22,"column":1}},"children":[{"type":"paragraph","children":[{"type":"text","value":"Specific writing templates, including:","position":{"start":{"line":14,"column":1},"end":{"line":14,"column":1}},"key":"c1KqgwhvFN"}],"key":"L8hktUKPnE"},{"type":"list","ordered":false,"spread":false,"position":{"start":{"line":15,"column":1},"end":{"line":22,"column":1}},"children":[{"type":"listItem","spread":true,"position":{"start":{"line":15,"column":1},"end":{"line":15,"column":1}},"children":[{"type":"paragraph","children":[{"type":"text","value":"Title and paragraph formatting","position":{"start":{"line":15,"column":1},"end":{"line":15,"column":1}},"key":"CHta9rWlRK"}],"key":"uTvoMTpErX"}],"key":"YlENXUkeD4"},{"type":"listItem","spread":true,"position":{"start":{"line":16,"column":1},"end":{"line":16,"column":1}},"children":[{"type":"paragraph","children":[{"type":"text","value":"Various admonition boxes (warning, thought, exercise)","position":{"start":{"line":16,"column":1},"end":{"line":16,"column":1}},"key":"F1RBFFDPMx"}],"key":"dqp0zF2rQ9"}],"key":"Dp9MKDZQ5C"},{"type":"listItem","spread":true,"position":{"start":{"line":17,"column":1},"end":{"line":17,"column":1}},"children":[{"type":"paragraph","children":[{"type":"text","value":"Inserting images and figure captions","position":{"start":{"line":17,"column":1},"end":{"line":17,"column":1}},"key":"uqogZ2YS7M"}],"key":"LHHpVnyeGs"}],"key":"hQkwqYDBNF"},{"type":"listItem","spread":true,"position":{"start":{"line":18,"column":1},"end":{"line":18,"column":1}},"children":[{"type":"paragraph","children":[{"type":"text","value":"Equations and references","position":{"start":{"line":18,"column":1},"end":{"line":18,"column":1}},"key":"MjIEWAzMAs"}],"key":"sTRwDuK9E8"}],"key":"MH5zzseW2o"},{"type":"listItem","spread":true,"position":{"start":{"line":19,"column":1},"end":{"line":19,"column":1}},"children":[{"type":"paragraph","children":[{"type":"text","value":"Tables and lists","position":{"start":{"line":19,"column":1},"end":{"line":19,"column":1}},"key":"x06OLtm65z"}],"key":"lygLwzTQPm"}],"key":"MhvLdJhdME"},{"type":"listItem","spread":true,"position":{"start":{"line":20,"column":1},"end":{"line":20,"column":1}},"children":[{"type":"paragraph","children":[{"type":"text","value":"Code blocks and executable ","position":{"start":{"line":20,"column":1},"end":{"line":20,"column":1}},"key":"bTkyTxJljL"},{"type":"inlineCode","value":"code-cell","position":{"start":{"line":20,"column":1},"end":{"line":20,"column":1}},"key":"k4kBeyEbjg"}],"key":"ipULMZj017"}],"key":"ZCCVT9n3B9"},{"type":"listItem","spread":true,"position":{"start":{"line":21,"column":1},"end":{"line":22,"column":1}},"children":[{"type":"paragraph","children":[{"type":"text","value":"Interactive plots/animations (output through Python)","position":{"start":{"line":21,"column":1},"end":{"line":21,"column":1}},"key":"n2782KGTwV"}],"key":"XoJdAjL82r"}],"key":"YUkHfgx7Fh"}],"key":"yILHqjOMb5"}],"key":"f3B2FySO77"}],"key":"N1smr9TpQI"},{"type":"admonition","kind":"note","children":[{"type":"admonitionTitle","children":[{"type":"text","value":"Note","key":"RDQSpOW4a2"}],"key":"PyXyGtBJcD"},{"type":"paragraph","position":{"start":{"line":24,"column":1},"end":{"line":24,"column":1}},"children":[{"type":"text","value":"You are free to modify the content and use it as a foundational writing template.","position":{"start":{"line":24,"column":1},"end":{"line":24,"column":1}},"key":"ucRlQX00zg"}],"key":"P1Xk19aKb7"}],"key":"OgN2UBe7vb"},{"type":"thematicBreak","position":{"start":{"line":27,"column":1},"end":{"line":27,"column":1}},"key":"SmpkMLqbWa"},{"type":"heading","depth":2,"position":{"start":{"line":29,"column":1},"end":{"line":29,"column":1}},"children":[{"type":"text","value":"The contents of this handbook are as follows","position":{"start":{"line":29,"column":1},"end":{"line":29,"column":1}},"key":"Nvgwsp8yEB"}],"identifier":"the-contents-of-this-handbook-are-as-follows","label":"The contents of this handbook are as follows","html_id":"the-contents-of-this-handbook-are-as-follows","implicit":true,"key":"gD6KegGElm"},{"type":"block","children":[{"type":"list","children":[{"type":"listItem","children":[{"type":"link","url":"/","internal":true,"children":[{"type":"text","value":"Book Writing Template📖","key":"g5uSgWDrZO"}],"urlSource":"/","key":"ZR34xLodS1"}],"key":"RAthL7e9x8"},{"type":"listItem","children":[{"type":"text","value":"English Content (EN)","key":"ulAaJLR9Og"},{"type":"list","children":[{"type":"listItem","children":[{"type":"link","url":"/writing-guide","internal":true,"children":[{"type":"text","value":"Knowledge Base Authoring Guide","key":"gUf5NwRSe3"}],"urlSource":"/writing-guide","key":"sP0knljfDH"}],"key":"vYy4L3uu33"},{"type":"listItem","children":[{"type":"link","url":"/ch1-mof-basics","internal":true,"children":[{"type":"text","value":"MOF Book Example Chapter 1 (Basics)","key":"T5m0Afu3IE"}],"urlSource":"/ch1-mof-basics","key":"HleoRvkX7h"}],"key":"y1w5eJBPF2"},{"type":"listItem","children":[{"type":"link","url":"/ch2-mof-advanced","internal":true,"children":[{"type":"text","value":"MOF Book Example Chapter 2 (Advanced)","key":"dM9j2mzguo"}],"urlSource":"/ch2-mof-advanced","key":"mCeuZMDtay"}],"key":"doxVCWUCM8"},{"type":"listItem","children":[{"type":"link","url":"/writing-template-basic","internal":true,"children":[{"type":"text","value":"Author Template - 1. Basics","key":"b9EzQDfEep"}],"urlSource":"/writing-template-basic","key":"rs1zaKTaDS"}],"key":"wvucFH2v3f"},{"type":"listItem","children":[{"type":"link","url":"/writing-template-code","internal":true,"children":[{"type":"text","value":"Author Template - 2. Code","key":"HB3PvjVDoj"}],"urlSource":"/writing-template-code","key":"r8EQ4P1T4Z"}],"key":"INQjk3dUvX"}],"key":"mI9mouTsxc"}],"key":"kFBP8Lh2eP"},{"type":"listItem","children":[{"type":"text","value":"中文内容 (ZH)","key":"qbyK92CmXx"},{"type":"list","children":[{"type":"listItem","children":[{"type":"link","url":"/writing-guide-zh","internal":true,"children":[{"type":"text","value":"开放知识库编写指南","key":"kaVhw6sXf5"}],"urlSource":"/writing-guide-zh","key":"NogSMpBlJ6"}],"key":"OyMvD9vMDm"},{"type":"listItem","children":[{"type":"link","url":"/writing-template-basic-zh","internal":true,"children":[{"type":"text","value":"写作者模板 - 1.基础","key":"MHMWPkzrwr"}],"urlSource":"/writing-template-basic-zh","key":"ENPTJ7CCcd"}],"key":"NvmokMPJUf"},{"type":"listItem","children":[{"type":"link","url":"/writing-template-code-zh","internal":true,"children":[{"type":"text","value":"写作者模板 - 2.代码","key":"Snrf7geEDJ"}],"urlSource":"/writing-template-code-zh","key":"Ol0M1JaEWb"}],"key":"Rcmb9kpASk"},{"type":"listItem","children":[{"type":"link","url":"/ch1-mof-basics-zh","internal":true,"children":[{"type":"text","value":"MOF书籍示例第一章（基础）","key":"FlhdAVc6j9"}],"urlSource":"/ch1-mof-basics-zh","key":"cLzPrTNNUL"}],"key":"zwY9QDwX04"},{"type":"listItem","children":[{"type":"link","url":"/ch2-mof-advanced-zh","internal":true,"children":[{"type":"text","value":"MOF书籍示例第二章（进阶）","key":"uXbKyi3OL1"}],"urlSource":"/ch2-mof-advanced-zh","key":"UJFs5bWEN4"}],"key":"FIXxtcRCCO"}],"key":"kd4TKcKCOE"}],"key":"XE1bCXrGc2"}],"key":"G2cbqzgcgW"}],"data":{"part":"toc:project"},"key":"JlNlvXJo8Y"}],"key":"AVKEh9owL1"}],"key":"n1wgj4N5vl"},"references":{"cite":{"order":[],"data":{}}}}