{"version":"1","myst":"1.7.1","references":[{"kind":"page","data":"/index.json","url":"/"},{"identifier":"welcome-to-the-mof-learning-handbook","kind":"heading","data":"/index.json","url":"/","implicit":true},{"identifier":"the-contents-of-this-handbook-are-as-follows","kind":"heading","data":"/index.json","url":"/","implicit":true},{"kind":"page","data":"/writing-guide.json","url":"/writing-guide"},{"identifier":"id-1-project-structure-overview","kind":"heading","data":"/writing-guide.json","url":"/writing-guide","implicit":true},{"identifier":"id-2-single-course-directory-structure","kind":"heading","data":"/writing-guide.json","url":"/writing-guide","implicit":true},{"identifier":"id-3-content-standards-and-formatting","kind":"heading","data":"/writing-guide.json","url":"/writing-guide","implicit":true},{"identifier":"id-4-how-to-add-chapters-edit-the-table-of-contents","kind":"heading","data":"/writing-guide.json","url":"/writing-guide","implicit":true},{"identifier":"id-4-1-steps-to-add-a-new-chapter","kind":"heading","data":"/writing-guide.json","url":"/writing-guide","implicit":true},{"identifier":"id-4-2-rearranging-chapter-order","kind":"heading","data":"/writing-guide.json","url":"/writing-guide","implicit":true},{"identifier":"id-5-local-preview-how-to-check-your-work","kind":"heading","data":"/writing-guide.json","url":"/writing-guide","implicit":true},{"identifier":"id-5-0-writing-workflow","kind":"heading","data":"/writing-guide.json","url":"/writing-guide","implicit":true},{"identifier":"id-5-1-environment-setup","kind":"heading","data":"/writing-guide.json","url":"/writing-guide","implicit":true},{"identifier":"id-5-2-building-a-single-course-book","kind":"heading","data":"/writing-guide.json","url":"/writing-guide","implicit":true},{"identifier":"id-5-3-local-preview-of-course","kind":"heading","data":"/writing-guide.json","url":"/writing-guide","implicit":true},{"identifier":"id-6-content-submission-workflow","kind":"heading","data":"/writing-guide.json","url":"/writing-guide","implicit":true},{"identifier":"id-6-1-submitting-files-directly","kind":"heading","data":"/writing-guide.json","url":"/writing-guide","implicit":true},{"identifier":"id-6-2-submitting-via-the-central-github-community","kind":"heading","data":"/writing-guide.json","url":"/writing-guide","implicit":true},{"identifier":"id-7-authoring-tips-and-best-practices","kind":"heading","data":"/writing-guide.json","url":"/writing-guide","implicit":true},{"identifier":"id-8-frequently-asked-questions-faq","kind":"heading","data":"/writing-guide.json","url":"/writing-guide","implicit":true},{"identifier":"id-9-not-sure-where-to-start","kind":"heading","data":"/writing-guide.json","url":"/writing-guide","implicit":true},{"kind":"page","data":"/ch1-mof-basics.json","url":"/ch1-mof-basics"},{"identifier":"chapter-1-basic-concepts-and-structure-of-mofs","kind":"heading","data":"/ch1-mof-basics.json","url":"/ch1-mof-basics","implicit":true},{"identifier":"id-1-1-what-is-a-mof","kind":"heading","data":"/ch1-mof-basics.json","url":"/ch1-mof-basics","implicit":true},{"identifier":"target-struct","kind":"heading","data":"/ch1-mof-basics.json","url":"/ch1-mof-basics"},{"identifier":"id-1-2-1-structure-illustration","kind":"heading","data":"/ch1-mof-basics.json","url":"/ch1-mof-basics","implicit":true},{"identifier":"fig-mof-schematic","kind":"figure","data":"/ch1-mof-basics.json","url":"/ch1-mof-basics"},{"identifier":"id-1-3-simple-crystallographic-expressions","kind":"heading","data":"/ch1-mof-basics.json","url":"/ch1-mof-basics","implicit":true},{"identifier":"id-1-3-1-volume-and-porosity","kind":"heading","data":"/ch1-mof-basics.json","url":"/ch1-mof-basics","implicit":true},{"identifier":"id-1-4-table-some-typical-mofs","kind":"heading","data":"/ch1-mof-basics.json","url":"/ch1-mof-basics","implicit":true},{"identifier":"tab-common-mofs","kind":"table","data":"/ch1-mof-basics.json","url":"/ch1-mof-basics"},{"identifier":"id-1-5-describing-mofs-with-python-code","kind":"heading","data":"/ch1-mof-basics.json","url":"/ch1-mof-basics","implicit":true},{"identifier":"id-1-6-calculating-the-relationship-between-porosity-and-pore-volume-in-python","kind":"heading","data":"/ch1-mof-basics.json","url":"/ch1-mof-basics","implicit":true},{"identifier":"id-1-7-simple-2d-plot-example","kind":"heading","data":"/ch1-mof-basics.json","url":"/ch1-mof-basics","implicit":true},{"identifier":"id-1-8-exercise-zone-task-list","kind":"heading","data":"/ch1-mof-basics.json","url":"/ch1-mof-basics","implicit":true},{"identifier":"exercise-pxip3fggjy","kind":"exercise","data":"/ch1-mof-basics.json","url":"/ch1-mof-basics"},{"identifier":"exercise-vx9h1jcx6t","kind":"exercise","data":"/ch1-mof-basics.json","url":"/ch1-mof-basics"},{"identifier":"exercise-rojwvoy4lb","kind":"exercise","data":"/ch1-mof-basics.json","url":"/ch1-mof-basics"},{"kind":"page","data":"/ch2-mof-advanced.json","url":"/ch2-mof-advanced"},{"identifier":"chapter-2-mof-adsorption-and-simulation","kind":"heading","data":"/ch2-mof-advanced.json","url":"/ch2-mof-advanced","implicit":true},{"identifier":"id-2-1-basics-of-adsorption-isotherms","kind":"heading","data":"/ch2-mof-advanced.json","url":"/ch2-mof-advanced","implicit":true},{"identifier":"id-2-2-visualization-of-mof-adsorption-isotherms","kind":"heading","data":"/ch2-mof-advanced.json","url":"/ch2-mof-advanced","implicit":true},{"identifier":"id-2-3-simulation-of-gas-molecule-diffusion-in-mof-channels","kind":"heading","data":"/ch2-mof-advanced.json","url":"/ch2-mof-advanced","implicit":true},{"identifier":"id-2-4-definitions-of-gas-molecule-behaviors-in-mof-channels","kind":"heading","data":"/ch2-mof-advanced.json","url":"/ch2-mof-advanced","implicit":true},{"identifier":"id-2-4-1-definitions-of-different-molecular-behaviors","kind":"heading","data":"/ch2-mof-advanced.json","url":"/ch2-mof-advanced","implicit":true},{"identifier":"id-2-4-2-brief-introduction-to-adsorption-process-simulation","kind":"heading","data":"/ch2-mof-advanced.json","url":"/ch2-mof-advanced","implicit":true},{"identifier":"id-2-5-simple-gcmc-simulation","kind":"heading","data":"/ch2-mof-advanced.json","url":"/ch2-mof-advanced","implicit":true},{"kind":"page","data":"/writing-template-basic.json","url":"/writing-template-basic"},{"identifier":"writing-syntax-section","kind":"heading","data":"/writing-template-basic.json","url":"/writing-template-basic","implicit":true},{"identifier":"id-0-document-frontmatter","kind":"heading","data":"/writing-template-basic.json","url":"/writing-template-basic","implicit":true},{"identifier":"id-1-typography","kind":"heading","data":"/writing-template-basic.json","url":"/writing-template-basic","implicit":true},{"identifier":"id-1-0","kind":"heading","data":"/writing-template-basic.json","url":"/writing-template-basic","implicit":true},{"identifier":"id-1-1-emphasis-and-inline-formatting","kind":"heading","data":"/writing-template-basic.json","url":"/writing-template-basic","implicit":true},{"identifier":"id-1-2-block-quote","kind":"heading","data":"/writing-template-basic.json","url":"/writing-template-basic","implicit":true},{"identifier":"id-1-3-horizontal-rule","kind":"heading","data":"/writing-template-basic.json","url":"/writing-template-basic","implicit":true},{"identifier":"id-1-4-footnotes","kind":"heading","data":"/writing-template-basic.json","url":"/writing-template-basic","implicit":true},{"identifier":"id-2-admonitions","kind":"heading","data":"/writing-template-basic.json","url":"/writing-template-basic","implicit":true},{"identifier":"id-2-1-tip","kind":"heading","data":"/writing-template-basic.json","url":"/writing-template-basic","implicit":true},{"identifier":"id-2-2-note","kind":"heading","data":"/writing-template-basic.json","url":"/writing-template-basic","implicit":true},{"identifier":"id-2-3-warning","kind":"heading","data":"/writing-template-basic.json","url":"/writing-template-basic","implicit":true},{"identifier":"id-2-4-general-admonition","kind":"heading","data":"/writing-template-basic.json","url":"/writing-template-basic","implicit":true},{"identifier":"id-3-figures","kind":"heading","data":"/writing-template-basic.json","url":"/writing-template-basic","implicit":true},{"identifier":"id-3-1-local-images","kind":"heading","data":"/writing-template-basic.json","url":"/writing-template-basic","implicit":true},{"identifier":"mof-structure","kind":"figure","data":"/writing-template-basic.json","url":"/writing-template-basic"},{"identifier":"id-3-2-web-images","kind":"heading","data":"/writing-template-basic.json","url":"/writing-template-basic","implicit":true},{"identifier":"wiki-mof","kind":"figure","data":"/writing-template-basic.json","url":"/writing-template-basic"},{"identifier":"id-4-math","kind":"heading","data":"/writing-template-basic.json","url":"/writing-template-basic","implicit":true},{"identifier":"id-4-1-inline-formulas","kind":"heading","data":"/writing-template-basic.json","url":"/writing-template-basic","implicit":true},{"identifier":"id-4-2-block-formulas","kind":"heading","data":"/writing-template-basic.json","url":"/writing-template-basic","implicit":true},{"identifier":"id-5-tables","kind":"heading","data":"/writing-template-basic.json","url":"/writing-template-basic","implicit":true},{"identifier":"id-5-1-standard-markdown-table","kind":"heading","data":"/writing-template-basic.json","url":"/writing-template-basic","implicit":true},{"identifier":"id-5-2-block-table","kind":"heading","data":"/writing-template-basic.json","url":"/writing-template-basic","implicit":true},{"identifier":"table","kind":"table","data":"/writing-template-basic.json","url":"/writing-template-basic"},{"identifier":"id-6-cross-references","kind":"heading","data":"/writing-template-basic.json","url":"/writing-template-basic","implicit":true},{"identifier":"id-7-external-references","kind":"heading","data":"/writing-template-basic.json","url":"/writing-template-basic","implicit":true},{"identifier":"id-8-embedding","kind":"heading","data":"/writing-template-basic.json","url":"/writing-template-basic","implicit":true},{"identifier":"id-9-citations","kind":"heading","data":"/writing-template-basic.json","url":"/writing-template-basic","implicit":true},{"identifier":"id-10-proofs-and-theorems","kind":"heading","data":"/writing-template-basic.json","url":"/writing-template-basic","implicit":true},{"identifier":"theorem-1","kind":"proof:theorem","data":"/writing-template-basic.json","url":"/writing-template-basic"},{"identifier":"proof-theorem-1","kind":"proof:proof","data":"/writing-template-basic.json","url":"/writing-template-basic"},{"identifier":"id-11-exercises","kind":"heading","data":"/writing-template-basic.json","url":"/writing-template-basic","implicit":true},{"identifier":"my-exercise","kind":"exercise","data":"/writing-template-basic.json","url":"/writing-template-basic"},{"identifier":"id-12-blocks-and-comments","kind":"heading","data":"/writing-template-basic.json","url":"/writing-template-basic","implicit":true},{"identifier":"id-12-1-blocks","kind":"heading","data":"/writing-template-basic.json","url":"/writing-template-basic","implicit":true},{"identifier":"id-12-2-comments","kind":"heading","data":"/writing-template-basic.json","url":"/writing-template-basic","implicit":true},{"identifier":"id-13-diagrams","kind":"heading","data":"/writing-template-basic.json","url":"/writing-template-basic","implicit":true},{"identifier":"id-14-asides","kind":"heading","data":"/writing-template-basic.json","url":"/writing-template-basic","implicit":true},{"identifier":"id-15-dropdowns-cards-tabs","kind":"heading","data":"/writing-template-basic.json","url":"/writing-template-basic","implicit":true},{"identifier":"id-15-1-dropdown","kind":"heading","data":"/writing-template-basic.json","url":"/writing-template-basic","implicit":true},{"identifier":"id-15-2-tabs","kind":"heading","data":"/writing-template-basic.json","url":"/writing-template-basic","implicit":true},{"identifier":"id-16-glossaries-and-terms","kind":"heading","data":"/writing-template-basic.json","url":"/writing-template-basic","implicit":true},{"identifier":"term-mof","kind":"definitionTerm","data":"/writing-template-basic.json","url":"/writing-template-basic"},{"identifier":"term-sbu","kind":"definitionTerm","data":"/writing-template-basic.json","url":"/writing-template-basic"},{"kind":"page","data":"/writing-template-code.json","url":"/writing-template-code"},{"identifier":"code-section","kind":"heading","data":"/writing-template-code.json","url":"/writing-template-code","implicit":true},{"identifier":"id-1-static-code-not-executed","kind":"heading","data":"/writing-template-code.json","url":"/writing-template-code","implicit":true},{"identifier":"id-2-executable-code-cell","kind":"heading","data":"/writing-template-code.json","url":"/writing-template-code","implicit":true},{"identifier":"id-3-add-metadata","kind":"heading","data":"/writing-template-code.json","url":"/writing-template-code","implicit":true},{"identifier":"id-3-1-hide-input-only-show-output","kind":"heading","data":"/writing-template-code.json","url":"/writing-template-code","implicit":true},{"identifier":"id-3-2-hide-output-only-show-code","kind":"heading","data":"/writing-template-code.json","url":"/writing-template-code","implicit":true},{"identifier":"id-3-3-completely-remove-input-code-is-invisible-in-the-final-webpage","kind":"heading","data":"/writing-template-code.json","url":"/writing-template-code","implicit":true},{"identifier":"id-3-4-completely-remove-output-output-not-visible-on-webpage","kind":"heading","data":"/writing-template-code.json","url":"/writing-template-code","implicit":true},{"identifier":"frequently-used-tags","kind":"heading","data":"/writing-template-code.json","url":"/writing-template-code","implicit":true},{"identifier":"id-4-plotting","kind":"heading","data":"/writing-template-code.json","url":"/writing-template-code","implicit":true},{"identifier":"id-5-interactive-visualization","kind":"heading","data":"/writing-template-code.json","url":"/writing-template-code","implicit":true},{"identifier":"id-6-pandas-table","kind":"heading","data":"/writing-template-code.json","url":"/writing-template-code","implicit":true},{"identifier":"id-7-structure-visualization-ase","kind":"heading","data":"/writing-template-code.json","url":"/writing-template-code","implicit":true},{"identifier":"id-7-1-build-molecule-via-ase-and-show-interactively","kind":"heading","data":"/writing-template-code.json","url":"/writing-template-code","implicit":true},{"identifier":"id-7-2-read-and-show-structure-from-local-file-cif-poscar-etc","kind":"heading","data":"/writing-template-code.json","url":"/writing-template-code","implicit":true},{"kind":"page","data":"/intro-zh.json","url":"/intro-zh"},{"identifier":"id-mof","kind":"heading","data":"/intro-zh.json","url":"/intro-zh","implicit":true},{"identifier":"id","kind":"heading","data":"/intro-zh.json","url":"/intro-zh","implicit":true},{"kind":"page","data":"/writing-guide-zh.json","url":"/writing-guide-zh"},{"identifier":"id-1","kind":"heading","data":"/writing-guide-zh.json","url":"/writing-guide-zh","implicit":true},{"identifier":"id-2","kind":"heading","data":"/writing-guide-zh.json","url":"/writing-guide-zh","implicit":true},{"identifier":"id-3","kind":"heading","data":"/writing-guide-zh.json","url":"/writing-guide-zh","implicit":true},{"identifier":"id-4","kind":"heading","data":"/writing-guide-zh.json","url":"/writing-guide-zh","implicit":true},{"identifier":"id-4-1","kind":"heading","data":"/writing-guide-zh.json","url":"/writing-guide-zh","implicit":true},{"identifier":"id-4-2","kind":"heading","data":"/writing-guide-zh.json","url":"/writing-guide-zh","implicit":true},{"identifier":"id-5","kind":"heading","data":"/writing-guide-zh.json","url":"/writing-guide-zh","implicit":true},{"identifier":"id-5-0","kind":"heading","data":"/writing-guide-zh.json","url":"/writing-guide-zh","implicit":true},{"identifier":"id-5-1","kind":"heading","data":"/writing-guide-zh.json","url":"/writing-guide-zh","implicit":true},{"identifier":"id-5-2","kind":"heading","data":"/writing-guide-zh.json","url":"/writing-guide-zh","implicit":true},{"identifier":"id-5-3","kind":"heading","data":"/writing-guide-zh.json","url":"/writing-guide-zh","implicit":true},{"identifier":"id-6","kind":"heading","data":"/writing-guide-zh.json","url":"/writing-guide-zh","implicit":true},{"identifier":"id-6-1","kind":"heading","data":"/writing-guide-zh.json","url":"/writing-guide-zh","implicit":true},{"identifier":"id-6-2-github-community","kind":"heading","data":"/writing-guide-zh.json","url":"/writing-guide-zh","implicit":true},{"identifier":"id-7","kind":"heading","data":"/writing-guide-zh.json","url":"/writing-guide-zh","implicit":true},{"identifier":"id-8-faq","kind":"heading","data":"/writing-guide-zh.json","url":"/writing-guide-zh","implicit":true},{"identifier":"id-9","kind":"heading","data":"/writing-guide-zh.json","url":"/writing-guide-zh","implicit":true},{"kind":"page","data":"/writing-template-basic-zh.json","url":"/writing-template-basic-zh"},{"identifier":"id","kind":"heading","data":"/writing-template-basic-zh.json","url":"/writing-template-basic-zh","implicit":true},{"identifier":"id-0-document","kind":"heading","data":"/writing-template-basic-zh.json","url":"/writing-template-basic-zh","implicit":true},{"identifier":"id-1-typography","kind":"heading","data":"/writing-template-basic-zh.json","url":"/writing-template-basic-zh","implicit":true},{"identifier":"id-1-0","kind":"heading","data":"/writing-template-basic-zh.json","url":"/writing-template-basic-zh","implicit":true},{"identifier":"id-1-1","kind":"heading","data":"/writing-template-basic-zh.json","url":"/writing-template-basic-zh","implicit":true},{"identifier":"id-1-2-block-quote","kind":"heading","data":"/writing-template-basic-zh.json","url":"/writing-template-basic-zh","implicit":true},{"identifier":"id-1-3","kind":"heading","data":"/writing-template-basic-zh.json","url":"/writing-template-basic-zh","implicit":true},{"identifier":"id-1-4","kind":"heading","data":"/writing-template-basic-zh.json","url":"/writing-template-basic-zh","implicit":true},{"identifier":"id-2-admonitions","kind":"heading","data":"/writing-template-basic-zh.json","url":"/writing-template-basic-zh","implicit":true},{"identifier":"id-2-1-tip","kind":"heading","data":"/writing-template-basic-zh.json","url":"/writing-template-basic-zh","implicit":true},{"identifier":"id-2-2-note","kind":"heading","data":"/writing-template-basic-zh.json","url":"/writing-template-basic-zh","implicit":true},{"identifier":"id-2-3-warning","kind":"heading","data":"/writing-template-basic-zh.json","url":"/writing-template-basic-zh","implicit":true},{"identifier":"id-2-4-admonition","kind":"heading","data":"/writing-template-basic-zh.json","url":"/writing-template-basic-zh","implicit":true},{"identifier":"id-3-figures","kind":"heading","data":"/writing-template-basic-zh.json","url":"/writing-template-basic-zh","implicit":true},{"identifier":"id-3-1","kind":"heading","data":"/writing-template-basic-zh.json","url":"/writing-template-basic-zh","implicit":true},{"identifier":"mof-structure-zh","kind":"figure","data":"/writing-template-basic-zh.json","url":"/writing-template-basic-zh"},{"identifier":"id-3-2","kind":"heading","data":"/writing-template-basic-zh.json","url":"/writing-template-basic-zh","implicit":true},{"identifier":"wiki-mof-zh","kind":"figure","data":"/writing-template-basic-zh.json","url":"/writing-template-basic-zh"},{"identifier":"id-4-math","kind":"heading","data":"/writing-template-basic-zh.json","url":"/writing-template-basic-zh","implicit":true},{"identifier":"id-4-1","kind":"heading","data":"/writing-template-basic-zh.json","url":"/writing-template-basic-zh","implicit":true},{"identifier":"id-4-2","kind":"heading","data":"/writing-template-basic-zh.json","url":"/writing-template-basic-zh","implicit":true},{"identifier":"id-5-tables","kind":"heading","data":"/writing-template-basic-zh.json","url":"/writing-template-basic-zh","implicit":true},{"identifier":"id-5-1-markdown","kind":"heading","data":"/writing-template-basic-zh.json","url":"/writing-template-basic-zh","implicit":true},{"identifier":"id-5-2-block","kind":"heading","data":"/writing-template-basic-zh.json","url":"/writing-template-basic-zh","implicit":true},{"identifier":"table-zh","kind":"table","data":"/writing-template-basic-zh.json","url":"/writing-template-basic-zh"},{"identifier":"id-6-cross-references","kind":"heading","data":"/writing-template-basic-zh.json","url":"/writing-template-basic-zh","implicit":true},{"identifier":"id-7-external-references","kind":"heading","data":"/writing-template-basic-zh.json","url":"/writing-template-basic-zh","implicit":true},{"identifier":"id-8-embedding","kind":"heading","data":"/writing-template-basic-zh.json","url":"/writing-template-basic-zh","implicit":true},{"identifier":"id-9-citations","kind":"heading","data":"/writing-template-basic-zh.json","url":"/writing-template-basic-zh","implicit":true},{"identifier":"id-10-proofs-and-theorems","kind":"heading","data":"/writing-template-basic-zh.json","url":"/writing-template-basic-zh","implicit":true},{"identifier":"theorem-1-zh","kind":"proof:theorem","data":"/writing-template-basic-zh.json","url":"/writing-template-basic-zh"},{"identifier":"proof-theorem-1-zh","kind":"proof:proof","data":"/writing-template-basic-zh.json","url":"/writing-template-basic-zh"},{"identifier":"id-11-exercises","kind":"heading","data":"/writing-template-basic-zh.json","url":"/writing-template-basic-zh","implicit":true},{"identifier":"my-exercise-zh","kind":"exercise","data":"/writing-template-basic-zh.json","url":"/writing-template-basic-zh"},{"identifier":"id-12-blocks-and-comments","kind":"heading","data":"/writing-template-basic-zh.json","url":"/writing-template-basic-zh","implicit":true},{"identifier":"id-12-1-blocks","kind":"heading","data":"/writing-template-basic-zh.json","url":"/writing-template-basic-zh","implicit":true},{"identifier":"id-12-2-comments","kind":"heading","data":"/writing-template-basic-zh.json","url":"/writing-template-basic-zh","implicit":true},{"identifier":"id-13-diagrams","kind":"heading","data":"/writing-template-basic-zh.json","url":"/writing-template-basic-zh","implicit":true},{"identifier":"id-14-asides","kind":"heading","data":"/writing-template-basic-zh.json","url":"/writing-template-basic-zh","implicit":true},{"identifier":"id-15-dropdowns-cards-tabs","kind":"heading","data":"/writing-template-basic-zh.json","url":"/writing-template-basic-zh","implicit":true},{"identifier":"id-15-1","kind":"heading","data":"/writing-template-basic-zh.json","url":"/writing-template-basic-zh","implicit":true},{"identifier":"id-15-2-tabs","kind":"heading","data":"/writing-template-basic-zh.json","url":"/writing-template-basic-zh","implicit":true},{"identifier":"id-16-glossaries-and-terms","kind":"heading","data":"/writing-template-basic-zh.json","url":"/writing-template-basic-zh","implicit":true},{"identifier":"term-mof-zh","kind":"definitionTerm","data":"/writing-template-basic-zh.json","url":"/writing-template-basic-zh"},{"identifier":"term-sbu-zh","kind":"definitionTerm","data":"/writing-template-basic-zh.json","url":"/writing-template-basic-zh"},{"kind":"page","data":"/writing-template-code-zh.json","url":"/writing-template-code-zh"},{"identifier":"id","kind":"heading","data":"/writing-template-code-zh.json","url":"/writing-template-code-zh","implicit":true},{"identifier":"id-1","kind":"heading","data":"/writing-template-code-zh.json","url":"/writing-template-code-zh","implicit":true},{"identifier":"id-2-code-cell","kind":"heading","data":"/writing-template-code-zh.json","url":"/writing-template-code-zh","implicit":true},{"identifier":"id-3","kind":"heading","data":"/writing-template-code-zh.json","url":"/writing-template-code-zh","implicit":true},{"identifier":"id-3-1","kind":"heading","data":"/writing-template-code-zh.json","url":"/writing-template-code-zh","implicit":true},{"identifier":"id-3-2","kind":"heading","data":"/writing-template-code-zh.json","url":"/writing-template-code-zh","implicit":true},{"identifier":"id-3-3","kind":"heading","data":"/writing-template-code-zh.json","url":"/writing-template-code-zh","implicit":true},{"identifier":"id-3-4","kind":"heading","data":"/writing-template-code-zh.json","url":"/writing-template-code-zh","implicit":true},{"identifier":"id-tags","kind":"heading","data":"/writing-template-code-zh.json","url":"/writing-template-code-zh","implicit":true},{"identifier":"id-4-plotting","kind":"heading","data":"/writing-template-code-zh.json","url":"/writing-template-code-zh","implicit":true},{"identifier":"id-5-interactive-visualization","kind":"heading","data":"/writing-template-code-zh.json","url":"/writing-template-code-zh","implicit":true},{"identifier":"id-6-pandas","kind":"heading","data":"/writing-template-code-zh.json","url":"/writing-template-code-zh","implicit":true},{"identifier":"id-7-ase","kind":"heading","data":"/writing-template-code-zh.json","url":"/writing-template-code-zh","implicit":true},{"identifier":"id-7-1-ase","kind":"heading","data":"/writing-template-code-zh.json","url":"/writing-template-code-zh","implicit":true},{"identifier":"id-7-2-cif-poscar","kind":"heading","data":"/writing-template-code-zh.json","url":"/writing-template-code-zh","implicit":true},{"kind":"page","data":"/ch1-mof-basics-zh.json","url":"/ch1-mof-basics-zh"},{"identifier":"id-mof","kind":"heading","data":"/ch1-mof-basics-zh.json","url":"/ch1-mof-basics-zh","implicit":true},{"identifier":"id-1-1-mof","kind":"heading","data":"/ch1-mof-basics-zh.json","url":"/ch1-mof-basics-zh","implicit":true},{"identifier":"target-struct-zh","kind":"heading","data":"/ch1-mof-basics-zh.json","url":"/ch1-mof-basics-zh"},{"identifier":"id-1-2-1","kind":"heading","data":"/ch1-mof-basics-zh.json","url":"/ch1-mof-basics-zh","implicit":true},{"identifier":"fig-mof-schematic-zh","kind":"figure","data":"/ch1-mof-basics-zh.json","url":"/ch1-mof-basics-zh"},{"identifier":"id-1-3","kind":"heading","data":"/ch1-mof-basics-zh.json","url":"/ch1-mof-basics-zh","implicit":true},{"identifier":"id-1-3-1","kind":"heading","data":"/ch1-mof-basics-zh.json","url":"/ch1-mof-basics-zh","implicit":true},{"identifier":"id-1-4-mof","kind":"heading","data":"/ch1-mof-basics-zh.json","url":"/ch1-mof-basics-zh","implicit":true},{"identifier":"tab-common-mofs-zh","kind":"table","data":"/ch1-mof-basics-zh.json","url":"/ch1-mof-basics-zh"},{"identifier":"id-1-5-python-mof","kind":"heading","data":"/ch1-mof-basics-zh.json","url":"/ch1-mof-basics-zh","implicit":true},{"identifier":"id-1-6-python","kind":"heading","data":"/ch1-mof-basics-zh.json","url":"/ch1-mof-basics-zh","implicit":true},{"identifier":"id-1-7-2d","kind":"heading","data":"/ch1-mof-basics-zh.json","url":"/ch1-mof-basics-zh","implicit":true},{"identifier":"id-1-8-task-list","kind":"heading","data":"/ch1-mof-basics-zh.json","url":"/ch1-mof-basics-zh","implicit":true},{"identifier":"exercise-kvty4ht8qs","kind":"exercise","data":"/ch1-mof-basics-zh.json","url":"/ch1-mof-basics-zh"},{"identifier":"exercise-uxjntljyqi","kind":"exercise","data":"/ch1-mof-basics-zh.json","url":"/ch1-mof-basics-zh"},{"identifier":"exercise-ifbpzq1qin","kind":"exercise","data":"/ch1-mof-basics-zh.json","url":"/ch1-mof-basics-zh"},{"kind":"page","data":"/ch2-mof-advanced-zh.json","url":"/ch2-mof-advanced-zh"},{"identifier":"id-mof","kind":"heading","data":"/ch2-mof-advanced-zh.json","url":"/ch2-mof-advanced-zh","implicit":true},{"identifier":"id-2-1","kind":"heading","data":"/ch2-mof-advanced-zh.json","url":"/ch2-mof-advanced-zh","implicit":true},{"identifier":"id-2-2-mof","kind":"heading","data":"/ch2-mof-advanced-zh.json","url":"/ch2-mof-advanced-zh","implicit":true},{"identifier":"id-2-3-mof","kind":"heading","data":"/ch2-mof-advanced-zh.json","url":"/ch2-mof-advanced-zh","implicit":true},{"identifier":"id-2-4-mof","kind":"heading","data":"/ch2-mof-advanced-zh.json","url":"/ch2-mof-advanced-zh","implicit":true},{"identifier":"id-2-4-1","kind":"heading","data":"/ch2-mof-advanced-zh.json","url":"/ch2-mof-advanced-zh","implicit":true},{"identifier":"id-2-4-2","kind":"heading","data":"/ch2-mof-advanced-zh.json","url":"/ch2-mof-advanced-zh","implicit":true},{"identifier":"id-2-5-gcmc","kind":"heading","data":"/ch2-mof-advanced-zh.json","url":"/ch2-mof-advanced-zh","implicit":true}]}